{
  "name": "Lela Carroll",
  "age": 36,
  "address": {
    "street": "Bule Court",
    "city": "Denikra",
    "state": "WA",
    "zip": "94889"
  },
  "contact": {
    "phone": "(453) 308-2251",
    "servicePhone": "800693864"
  },
  "birthday": "1978-03-14T02:48:22.984Z",
  "ip": "92.39.12.98",
  "foo": "bar",
  "profile": {
    "about": "Sonep tuwipik miov inomfi geh du farsij duhjeb jali bonin wecmef lonepi ka vojcujus ke me ojumled. Cukezwet iti neelebon ekecere uz etihovro seaja vihpun kiv pujzuwsul dofum fi hur hih gabir fo. Zaip ruvug ha vu fuh muegsa fiid ogo imnefta jokvan telvac tav idhikke. Pad ow epu zonwewlo jewi reuzotis jumasi atih no fic mudopopil jafuw lizif. Cukmuwij nav gew sivodop fozvirice bos nehejel duezopu vutuw hebara ak iruma.",
    "bio": "Idi robvoh ruve hafver cilig kuipgi ja esaz tog se te je di ojaget. Jutbewmi nawde hiz misrewwo munke bivevhi ekmad ohemuti hepike ho edu ludnijinu za. Wada rubutur tej cazlu nur kicepe jakopu tizaspec zutraha maheufe tod uf ez fu warep. Elawoeh gab mef jeb pazhokid soot omvavi tuaho wepvazpuj cuhu wapdijmi karlof jazjiv nuinisap zi uzupo vuwto. Minzi lek bo orere wonituji banav sopke jat awu kuwu helod jemcid pud naahbok."
  },
  "apiKey": "293c4c24343326ab9a1fb89a191a315970d8c39f7f4adf44b845eccf3f02122b",
  "currency": {
    "code": "GYD",
    "name": "Guyana Dollar"
  }
}