{
  "name": "Lela Douglas",
  "age": 51,
  "address": {
    "street": "Dohe Pike",
    "city": "Kevmipuve",
    "state": "NM",
    "zip": "21739"
  },
  "contact": {
    "phone": "(462) 714-7177",
    "servicePhone": "800527964"
  },
  "birthday": "1967-03-31T07:07:58.263Z",
  "ip": "115.191.131.87",
  "foo": "bar",
  "profile": {
    "about": "Kif en nuslew ter guhjujus minvadiz rabiw namwizran ab ez sic nif ubatovu jesodeutu ohico iz. Molinco fizmutip geb cajvecaf te hu ejodo cec jitora jicotum piuhre bolol ernajzaz rowdirpe ribah nedapi gera nesgehu. Ac pos subecad esu iva vikiulo bu sotat bakolaro tas bauwe fe bome de il ererof gahikjod gov. Wacu folvasfo ewahir porvarer mo he fec pum vas wumenun zuzzum zokaleca ziigece wuc kuzfadju nic wefe le.",
    "bio": "Sitlu sog elheeni ojjiz de dafoner wobu jawguab ekopordop bujsuhon gono zogcirmof. Icutos bolu nu fav niruv hakvab fa odji jaoko rescur amu wuvu sersen liv. Veso kov pevirnof vol fuvedeva muawa jiupte jufabeilu imos pode copmo ab odejicis ukuhatab bauhwip ba delduwepe hin."
  },
  "apiKey": "356c729d149b730c75c177b6f4fff1bd19bedbeb66f937b6b538d91bf695adf2",
  "currency": {
    "code": "GBP",
    "name": "United Kingdom Pound"
  }
}