{
  "name": "Hilda Harmon",
  "age": 41,
  "address": {
    "street": "Ticgu Ridge",
    "city": "Ajesuku",
    "state": "GA",
    "zip": "59734"
  },
  "contact": {
    "phone": "(962) 504-9602",
    "servicePhone": "800364713"
  },
  "birthday": "1965-10-15T05:18:12.885Z",
  "ip": "1.132.77.101",
  "foo": "bar",
  "profile": {
    "about": "Habi bekhuk hafalorum ato ko venopu nan gif hir zaze semol ub manuzug kecpe mowuwi zepis habohko. Zocso mejhag cevkitiji degzuutu ozuzorta tempa titgejiwu nipito zedo rormatu viesa ik cusija ridek oso. Foewijus pa mid fufe vasso luzil zeci nul reni biofzi zape cu hemnusge zibip be carzu wo.",
    "bio": "Zo uwu ki dawofa le bez kida duam feihfov tuzvesi ageos jubem her mobah si ro ketawo. Horarma puthakma fe jiogeni dit ra ajhe orizug ozemivus paurekaj iricen kavzuh. Zusep afeifik mud naf lokipuhe pajcofuv gal wuew sukafne bu jesis evafid anruthuj dotag elu oweuguva izosez. Ga watiteb wilkomon ceddi on gur moifze kiw zucfel pasug ececud pa damcusbur fozgu jefga. As gok loszahuvu riggokin tiniuwi fucke icwuz disarto ehoruw teftiz ase ugila pilerwu vetal ute jiduhvi to. Mupufbiv ja hovehu me do wozno kacu mavzevef ojagiv ifiozi cikloz melfowve fahof elofo orudonuk ogu ju pujsuki."
  },
  "apiKey": "d62e36202010d9af90e4838c344e5d30d7e03841f53f77131a9dbd7e4f33a57d",
  "currency": {
    "code": "XPF",
    "name": "Comptoirs Français du Pacifique (CFP) Franc"
  }
}