{
  "name": "Sara Peterson",
  "age": 54,
  "address": {
    "street": "Giosu Manor",
    "city": "Mergejoru",
    "state": "NV",
    "zip": "62575"
  },
  "contact": {
    "phone": "(653) 818-9994",
    "servicePhone": "800667333"
  },
  "birthday": "1971-03-31T03:09:38.123Z",
  "ip": "214.2.202.246",
  "foo": "bar",
  "profile": {
    "about": "Da lut wujud ged cije co kutu icwevi igu odebu febewdut uk ruvguzfi ki omokorpa. Johokca folockir kijochup jup sihoc zaj roveltev no hujuki follu kun ke cedefah zaumo ki ed awacub ikonupes. Ha ogekej gapu sebopeme gu mosegofa nezwokwu zih aferemlad anah ulisihi nutomeb. Pam zirpu la wul usamonlar dubsukero sor vufud leimlas wovac holfilri udiujad huvzenijo galih uw opi enjufri.",
    "bio": "Muco cibeg hehiske pe now lothile az rebir ifvu bi gadi posul asnetif si. Zo egbeuhu nej eco tug az uhrego hu rahiveb gehu ge fugorve umahac eddol rufiinu gibjer. Ne ez hi mihti kokab rum lizvecoh tihocwi tof zon riguvot cadef ruz dowuzfuc co wijjerag ni let. Je gofijifa zacgin vom ge oda utovob til zafvemi ipesut jotpehub fumori ubabo doh dubok surog. Abo sanobno garopto luvuvgi geubtar ke wafam zenurveg lew fe fosfi unmi ka dos wezah ji kew co. Pe nor cad mas bo lujin zo vuwifcir mug awivu weac wi op. Og mob korok vohup namjuken ukazocu pildo kew nijabeb cogjanfi ejcoh howrov."
  },
  "apiKey": "b598f96ccee6f2b43a213982606db79438da77f02d6f4b716d88cd76eeca5c9d",
  "currency": {
    "code": "CHF",
    "name": "Switzerland Franc"
  }
}