{
  "name": "Edward Johnson",
  "age": 50,
  "address": {
    "street": "Honnum Boulevard",
    "city": "Zofnama",
    "state": "TN",
    "zip": "13891"
  },
  "contact": {
    "phone": "(316) 877-1937",
    "servicePhone": "800674663"
  },
  "birthday": "1974-10-18T04:11:03.124Z",
  "ip": "214.57.19.167",
  "foo": "bar",
  "profile": {
    "about": "Coze ha cut zup kutja gewdise conotfu otwez rimguh cizzopwev reim bo. Navpasza ameevanin bo akelu be itmonu muofubif batu vuflufle vazkoz gasigbor uj budnirviz kocathan. Uc zogu elalolim tisagar cadzaoco ti wugoro nulmib jus ohpur emcedkag tipate.",
    "bio": "Abe umvejala co weicu oconaawi naeho niw wutumione bi nenodduf mibeij nesful ibeomu. Ap heulaw vejec nojvodji sa pujosuwi bogig basit al ved onecowi di zazpasa reviku gus es moshuesa ta. Cakapji ne vorav saikke zig notarpi hitjiv kucab keillu wiebiov oce kedum nub ijosul kulauc ciche be. Pavnereco ki raluro arbu rodipcoz kanniv cerap vuz piuvi levav afku arnafeg lacto vuf viwca in fiwcu latajik. Alo irogu ca woopfiz husoke fitom appej hevujmop sehof to jiniv rude. La jic mohurjub lu pok co vu ziez emgidul eg vage fezwoj du fulpuhel zilit ohufhoz fajsiome."
  },
  "apiKey": "c5ea8fd8543d825c6217c1dcab60ef368ce04a0b6216b8f4b1b272914f1bd171",
  "currency": {
    "code": "UGX",
    "name": "Uganda Shilling"
  }
}