{
  "name": "Steven Gordon",
  "age": 44,
  "address": {
    "street": "Foka Boulevard",
    "city": "Ifumueso",
    "state": "ND",
    "zip": "05128"
  },
  "contact": {
    "phone": "(419) 847-3128",
    "servicePhone": "800667463"
  },
  "birthday": "1959-04-29T01:50:15.379Z",
  "ip": "75.202.58.227",
  "foo": "bar",
  "profile": {
    "about": "Fipompa ok co vezfucbe at teh viciwa de sa catfo uda vocala. Cehvehi uvoji bif zosasev jiplew cisso himbev omo hu rifzo deima paz osonomvi unezitat. Bogidide tik joni cucodewew socowjum dapfugu wa baszoz kuziwov tucracbo ugvav mogoro dezvef. Agtozwab gouku hav dazhi kup mojeda soncula turlig da nigekzu celohco wucjewnav hijdag amimi jukuw rewisag odboj sav. Jejgovek juifise afemazo wobifwum tisfoti jerki macu we nuvfu neoju cez fanni.",
    "bio": "Mu japiw kil buvfiknoh oksahze buw ze olodov na wameh ralgioku ewsiv cisu kufaro ufeire sandew pusogo bazaw. Gujowci jijiipa joiba vacenac fo bew hus niut ini abcug naba dumnazgir fitim buzewa ofged egeg do. Pesalu bolujne teagovi ru gu odu guef fev kizno kap emmerig vungem minuw jorle heffuhbe."
  },
  "apiKey": "384d203507c25bafe35a89e638a3c85cafd7ebf5c02a545d51cc2a881f5434c7",
  "currency": {
    "code": "MGA",
    "name": "Madagascar Ariary"
  }
}